{
  "repository": "Git",
  "url": "https://github.com/kishikawakatsumi/swift-power-assert",
  "path": "swift-power-assert",
  "branch": "main",
  "maintainer": "kishikawakatsumi@mac.com",
  "compatibility": [
    {
      "version": "5.9",
      "commit": "e06a8c7588b01957228a59d5009fd24c31f6de38"
    }
  ],
  "platforms": [
    "Darwin",
    "Windows"
  ],
  "actions": [
    {
      "action": "BuildSwiftPackage",
      "configuration": "release",
      "tags": "sourcekit sourcekit-smoke"
    },
    {
      "action": "TestSwiftPackage"
    }
  ]
}