[
  {
    "path" : "*\/Result\/Result\/Result.swift",
    "issueDetail" : {
      "kind" : "codeComplete",
      "offset" : 7449
    },
    "applicableConfigs" : [
      "main", "release/5.10", "release/5.9"
    ],
    "issueUrl" : "https://github.com/apple/swift/issues/51404"
  },
  {
    "path" : "*\/Result\/Result\/Result.swift",
    "issueDetail" : {
      "kind" : "codeComplete",
      "offset" : 7836
    },
    "applicableConfigs" : [
      "main", "release/5.10", "release/5.9"
    ],
    "issueUrl" : "https://github.com/apple/swift/issues/51404"
  },
  {
    "path" : "*\/Result\/Result\/Result.swift",
    "issueDetail" : {
      "kind" : "codeComplete",
      "offset" : 8038
    },
    "applicableConfigs" : [
      "main", "release/5.10", "release/5.9"
    ],
    "issueUrl" : "https://github.com/apple/swift/issues/51404"
  },
  {
    "path" : "*\/Result\/Tests\/ResultTests\/ResultTests.swift",
    "modification" : "unmodified",
    "issueDetail" : {
      "kind" : "codeComplete",
      "offset" : 79
    },
    "applicableConfigs" : [
      "main", "release/5.10", "release/5.9"
    ],
    "issueUrl" : "https://github.com/apple/swift/issues/51404"
  },
  {
    "path" : "*\/Result\/Tests\/ResultTests\/ResultTests.swift",
    "modification" : "unmodified",
    "issueDetail" : {
      "kind" : "codeComplete",
      "offset" : 5606
    },
    "applicableConfigs" : [
      "main", "release/5.10", "release/5.9"
    ],
    "issueUrl" : "https://github.com/apple/swift/issues/51404"
  },
  {
    "path" : "*\/DNS\/Sources\/DNS\/Integer+Data.swift",
    "issueDetail" : {
      "kind" : "codeComplete",
      "offset" : 194
    },
    "applicableConfigs" : [
      "main", "release/5.10", "release/5.9"
    ],
    "issueUrl" : "https://github.com/apple/swift/issues/56898"
  },
  {
    "path" : "*\/ACHNBrowserUI\/ACHNBrowserUI\/ACHNBrowserUI\/packages\/Backend\/Sources\/Backend\/models\/Villager.swift",
    "modification" : "concurrent-658",
    "issueDetail" : {
      "kind" : "collectExpressionType"
    },
    "applicableConfigs" : [
      "main", "release/5.10", "release/5.9"
    ],
    "issueUrl" : "https://github.com/apple/swift/issues/57045"
  },
  {
    "path" : "*\/ACHNBrowserUI\/ACHNBrowserUI\/ACHNBrowserUI\/packages\/Backend\/Sources\/Backend\/models\/Villager.swift",
    "modification" : "concurrent-824",
    "issueDetail" : {
      "kind" : "collectExpressionType"
    },
    "applicableConfigs" : [
      "main", "release/5.10", "release/5.9"
    ],
    "issueUrl" : "https://github.com/apple/swift/issues/57045"
  },
  {
    "path" : "*\/ACHNBrowserUI\/ACHNBrowserUI\/ACHNBrowserUI\/packages\/Backend\/Sources\/Backend\/models\/Villager.swift",
    "modification" : "concurrent-548",
    "issueDetail" : {
      "kind" : "collectExpressionType"
    },
    "applicableConfigs" : [
      "main", "release/5.10", "release/5.9"
    ],
    "issueUrl" : "https://github.com/apple/swift/issues/57045"
  },
  {
    "path" : "*\/ACHNBrowserUI\/ACHNBrowserUI\/ACHNBrowserUI\/packages\/Backend\/Sources\/Backend\/models\/Villager.swift",
    "modification" : "concurrent-1311",
    "issueDetail" : {
      "kind" : "collectExpressionType"
    },
    "applicableConfigs" : [
      "main", "release/5.10", "release/5.9"
    ],
    "issueUrl" : "https://github.com/apple/swift/issues/57045"
  },
  {
    "path" : "*\/ACHNBrowserUI\/ACHNBrowserUI\/ACHNBrowserUI\/packages\/Backend\/Sources\/Backend\/models\/Villager.swift",
    "modification" : "concurrent-736",
    "issueDetail" : {
      "kind" : "collectExpressionType"
    },
    "applicableConfigs" : [
      "main", "release/5.10", "release/5.9"
    ],
    "issueUrl" : "https://github.com/apple/swift/issues/57045"
  },
  {
    "path" : "*\/ACHNBrowserUI\/ACHNBrowserUI\/ACHNBrowserUI\/packages\/Backend\/Sources\/Backend\/models\/Villager.swift",
    "modification" : "concurrent-1699",
    "issueDetail" : {
      "kind" : "collectExpressionType"
    },
    "applicableConfigs" : [
      "main", "release/5.10", "release/5.9"
    ],
    "issueUrl" : "https://github.com/apple/swift/issues/57045"
  },
  {
    "path" : "*\/ACHNBrowserUI\/ACHNBrowserUI\/ACHNBrowserUI\/packages\/Backend\/Sources\/Backend\/models\/Villager.swift",
    "modification" : "concurrent-352",
    "issueDetail" : {
      "kind" : "rangeInfo",
      "length" : 5,
      "offset" : 248
    },
    "applicableConfigs" : [
      "main", "release/5.10", "release/5.9"
    ],
    "issueUrl" : "https://github.com/apple/swift/issues/57045"
  },
  {
    "path" : "*\/ACHNBrowserUI\/ACHNBrowserUI\/ACHNBrowserUI\/packages\/Backend\/Sources\/Backend\/models\/Villager.swift",
    "modification" : "concurrent-352",
    "issueDetail" : {
      "kind" : "cursorInfo",
      "offset" : 250
    },
    "applicableConfigs" : [
      "main", "release/5.10", "release/5.9"
    ],
    "issueUrl" : "https://github.com/apple/swift/issues/57045"
  },
  {
    "path" : "*\/ACHNBrowserUI\/ACHNBrowserUI\/ACHNBrowserUI\/packages\/Backend\/Sources\/Backend\/models\/Villager.swift",
    "modification" : "concurrent-439",
    "issueDetail" : {
      "kind" : "cursorInfo",
      "offset" : 279
    },
    "applicableConfigs" : [
      "main", "release/5.10", "release/5.9"
    ],
    "issueUrl" : "https://github.com/apple/swift/issues/57045"
  },
  {
    "path" : "*\/ACHNBrowserUI\/ACHNBrowserUI\/ACHNBrowserUI\/packages\/Backend\/Sources\/Backend\/models\/Villager.swift",
    "modification" : "concurrent-451",
    "issueDetail" : {
      "kind" : "rangeInfo",
      "length" : 7,
      "offset" : 279
    },
    "applicableConfigs" : [
      "main", "release/5.10", "release/5.9"
    ],
    "issueUrl" : "https://github.com/apple/swift/issues/57045"
  },
  {
    "path" : "*\/ACHNBrowserUI\/ACHNBrowserUI\/ACHNBrowserUI\/packages\/Backend\/Sources\/Backend\/models\/Villager.swift",
    "modification" : "concurrent-534",
    "issueDetail" : {
      "kind" : "cursorInfo",
      "offset" : 315
    },
    "applicableConfigs" : [
      "main", "release/5.10", "release/5.9"
    ],
    "issueUrl" : "https://github.com/apple/swift/issues/57045"
  },
  {
    "path" : "*\/ACHNBrowserUI\/ACHNBrowserUI\/ACHNBrowserUI\/packages\/Backend\/Sources\/Backend\/models\/Villager.swift",
    "modification" : "concurrent-536",
    "issueDetail" : {
      "kind" : "rangeInfo",
      "length" : 7,
      "offset" : 315
    },
    "applicableConfigs" : [
      "main", "release/5.10", "release/5.9"
    ],
    "issueUrl" : "https://github.com/apple/swift/issues/57045"
  },
  {
    "path" : "*\/ACHNBrowserUI\/ACHNBrowserUI\/ACHNBrowserUI\/packages\/Backend\/Sources\/Backend\/models\/Villager.swift",
    "modification" : "concurrent-697",
    "issueDetail" : {
      "kind" : "rangeInfo",
      "length" : 8,
      "offset" : 387
    },
    "applicableConfigs" : [
      "main", "release/5.10", "release/5.9"
    ],
    "issueUrl" : "https://github.com/apple/swift/issues/57045"
  },
  {
    "path" : "*\/ACHNBrowserUI\/ACHNBrowserUI\/ACHNBrowserUI\/packages\/Backend\/Sources\/Backend\/models\/Villager.swift",
    "modification" : "concurrent-697",
    "issueDetail" : {
      "kind" : "cursorInfo",
      "offset" : 389
    },
    "applicableConfigs" : [
      "main", "release/5.10", "release/5.9"
    ],
    "issueUrl" : "https://github.com/apple/swift/issues/57045"
  },
  {
    "path" : "*\/ACHNBrowserUI\/ACHNBrowserUI\/ACHNBrowserUI\/packages\/Backend\/Sources\/Backend\/models\/Villager.swift",
    "modification" : "concurrent-785",
    "issueDetail" : {
      "kind" : "rangeInfo",
      "length" : 7,
      "offset" : 421
    },
    "applicableConfigs" : [
      "main", "release/5.10", "release/5.9"
    ],
    "issueUrl" : "https://github.com/apple/swift/issues/57045"
  },
  {
    "path" : "*\/ACHNBrowserUI\/ACHNBrowserUI\/ACHNBrowserUI\/packages\/Backend\/Sources\/Backend\/models\/Villager.swift",
    "modification" : "concurrent-783",
    "issueDetail" : {
      "kind" : "cursorInfo",
      "offset" : 421
    },
    "applicableConfigs" : [
      "main", "release/5.10", "release/5.9"
    ],
    "issueUrl" : "https://github.com/apple/swift/issues/57045"
  },
  {
    "path" : "*\/ACHNBrowserUI\/ACHNBrowserUI\/ACHNBrowserUI\/packages\/Backend\/Sources\/Backend\/models\/Villager.swift",
    "modification" : "concurrent-784",
    "issueDetail" : {
      "kind" : "rangeInfo",
      "length" : 16,
      "offset" : 769
    },
    "applicableConfigs" : [
      "main", "release/5.10", "release/5.9"
    ],
    "issueUrl" : "https://github.com/apple/swift/issues/57045"
  },
  {
    "path" : "*\/ACHNBrowserUI\/ACHNBrowserUI\/ACHNBrowserUI\/packages\/Backend\/Sources\/Backend\/models\/Villager.swift",
    "modification" : "concurrent-1301",
    "issueDetail" : {
      "kind" : "rangeInfo",
      "length" : 8,
      "offset" : 828
    },
    "applicableConfigs" : [
      "main", "release/5.10", "release/5.9"
    ],
    "issueUrl" : "https://github.com/apple/swift/issues/57045"
  },
  {
    "path" : "*\/ACHNBrowserUI\/ACHNBrowserUI\/ACHNBrowserUI\/packages\/Backend\/Sources\/Backend\/models\/Villager.swift",
    "modification" : "concurrent-1301",
    "issueDetail" : {
      "kind" : "cursorInfo",
      "offset" : 830
    },
    "applicableConfigs" : [
      "main", "release/5.10", "release/5.9"
    ],
    "issueUrl" : "https://github.com/apple/swift/issues/57045"
  },
  {
    "path" : "*\/ACHNBrowserUI\/ACHNBrowserUI\/ACHNBrowserUI\/packages\/Backend\/Sources\/Backend\/models\/Villager.swift",
    "modification" : "concurrent-1689",
    "issueDetail" : {
      "kind" : "rangeInfo",
      "length" : 345,
      "offset" : 879
    },
    "applicableConfigs" : [
      "main", "release/5.10", "release/5.9"
    ],
    "issueUrl" : "https://github.com/apple/swift/issues/57045"
  },
  {
    "path" : "*\/ACHNBrowserUI\/ACHNBrowserUI\/ACHNBrowserUI\/packages\/Backend\/Sources\/Backend\/models\/Villager.swift",
    "modification" : "concurrent-676",
    "issueDetail" : {
      "kind" : "codeComplete",
      "offset" : 376
    },
    "applicableConfigs" : [
      "main", "release/5.10", "release/5.9"
    ],
    "issueUrl" : "https://github.com/apple/swift/issues/57045"
  },
  {
    "path" : "*\/ACHNBrowserUI\/ACHNBrowserUI\/ACHNBrowserUI\/packages\/Backend\/Sources\/Backend\/models\/Villager.swift",
    "modification" : "concurrent-763",
    "issueDetail" : {
      "kind" : "codeComplete",
      "offset" : 411
    },
    "applicableConfigs" : [
      "main", "release/5.10", "release/5.9"
    ],
    "issueUrl" : "https://github.com/apple/swift/issues/57045"
  },
  {
    "path" : "*\/ACHNBrowserUI\/ACHNBrowserUI\/ACHNBrowserUI\/packages\/Backend\/Sources\/Backend\/models\/Villager.swift",
    "modification" : "concurrent-849",
    "issueDetail" : {
      "kind" : "codeComplete",
      "offset" : 444
    },
    "applicableConfigs" : [
      "main", "release/5.10", "release/5.9"
    ],
    "issueUrl" : "https://github.com/apple/swift/issues/57045"
  },
  {
    "path" : "*\/ACHNBrowserUI\/ACHNBrowserUI\/ACHNBrowserUI\/packages\/Backend\/Sources\/Backend\/models\/Villager.swift",
    "modification" : "concurrent-1322",
    "issueDetail" : {
      "kind" : "codeComplete",
      "offset" : 857
    },
    "applicableConfigs" : [
      "main", "release/5.10", "release/5.9"
    ],
    "issueUrl" : "https://github.com/apple/swift/issues/57045"
  },
  {
    "path" : "*\/ACHNBrowserUI\/ACHNBrowserUI\/ACHNBrowserUI\/packages\/Backend\/Sources\/Backend\/models\/Villager.swift",
    "modification" : "concurrent-1337",
    "issueDetail" : {
      "kind" : "codeComplete",
      "offset" : 872
    },
    "applicableConfigs" : [
      "main", "release/5.10", "release/5.9"
    ],
    "issueUrl" : "https://github.com/apple/swift/issues/57045"
  },
  {
    "path" : "*\/ACHNBrowserUI\/ACHNBrowserUI\/ACHNBrowserUI\/packages\/Backend\/Sources\/Backend\/models\/Villager.swift",
    "modification" : "concurrent-1343",
    "issueDetail" : {
      "kind" : "codeComplete",
      "offset" : 878
    },
    "applicableConfigs" : [
      "main", "release/5.10", "release/5.9"
    ],
    "issueUrl" : "https://github.com/apple/swift/issues/57045"
  },
  {
    "path" : "*\/MovieSwift\/MovieSwift\/Shared\/flux\/models\/Movie.swift",
    "modification" : "concurrent-331",
    "issueDetail" : {
      "kind" : "collectExpressionType"
    },
    "applicableConfigs" : [
      "main", "release/5.10", "release/5.9"
    ],
    "issueUrl" : "https://github.com/apple/swift/issues/57045"
  },
  {
    "path" : "*\/MovieSwift\/MovieSwift\/Shared\/flux\/models\/Movie.swift",
    "modification" : "concurrent-471",
    "issueDetail" : {
      "kind" : "collectExpressionType"
    },
    "applicableConfigs" : [
      "main", "release/5.10", "release/5.9"
    ],
    "issueUrl" : "https://github.com/apple/swift/issues/57045"
  },
  {
    "path" : "*\/MovieSwift\/MovieSwift\/Shared\/flux\/models\/Movie.swift",
    "modification" : "concurrent-1874",
    "issueDetail" : {
      "kind" : "collectExpressionType"
    },
    "applicableConfigs" : [
      "main", "release/5.10", "release/5.9"
    ],
    "issueUrl" : "https://github.com/apple/swift/issues/57045"
  },
  {
    "path" : "*\/MovieSwift\/MovieSwift\/Shared\/flux\/models\/Movie.swift",
    "modification" : "concurrent-267",
    "issueDetail" : {
      "kind" : "collectExpressionType"
    },
    "applicableConfigs" : [
      "main", "release/5.10", "release/5.9"
    ],
    "issueUrl" : "https://github.com/apple/swift/issues/57045"
  },
  {
    "path" : "*\/MovieSwift\/MovieSwift\/Shared\/flux\/models\/Movie.swift",
    "modification" : "concurrent-442",
    "issueDetail" : {
      "kind" : "collectExpressionType"
    },
    "applicableConfigs" : [
      "main", "release/5.10", "release/5.9"
    ],
    "issueUrl" : "https://github.com/apple/swift/issues/57045"
  },
  {
    "path" : "*\/MovieSwift\/MovieSwift\/Shared\/flux\/models\/Movie.swift",
    "modification" : "concurrent-436",
    "issueDetail" : {
      "kind" : "rangeInfo",
      "length" : 8,
      "offset" : 277
    },
    "applicableConfigs" : [
      "main", "release/5.10", "release/5.9"
    ],
    "issueUrl" : "https://github.com/apple/swift/issues/57045"
  },
  {
    "path" : "*\/MovieSwift\/MovieSwift\/Shared\/flux\/models\/Movie.swift",
    "modification" : "concurrent-436",
    "issueDetail" : {
      "kind" : "cursorInfo",
      "offset" : 279
    },
    "applicableConfigs" : [
      "main", "release/5.10", "release/5.9"
    ],
    "issueUrl" : "https://github.com/apple/swift/issues/57045"
  },
  {
    "path" : "*\/MovieSwift\/MovieSwift\/Shared\/flux\/models\/Movie.swift",
    "modification" : "concurrent-437",
    "issueDetail" : {
      "kind" : "rangeInfo",
      "length" : 96,
      "offset" : 342
    },
    "applicableConfigs" : [
      "main", "release/5.10", "release/5.9"
    ],
    "issueUrl" : "https://github.com/apple/swift/issues/57045"
  },
  {
    "path" : "*\/MovieSwift\/MovieSwift\/Shared\/flux\/models\/Movie.swift",
    "modification" : "concurrent-612",
    "issueDetail" : {
      "kind" : "rangeInfo",
      "length" : 112,
      "offset" : 501
    },
    "applicableConfigs" : [
      "main", "release/5.10", "release/5.9"
    ],
    "issueUrl" : "https://github.com/apple/swift/issues/57045"
  },
  {
    "path" : "*\/MovieSwift\/MovieSwift\/Shared\/flux\/models\/Movie.swift",
    "modification" : "concurrent-1864",
    "issueDetail" : {
      "kind" : "rangeInfo",
      "length" : 6,
      "offset" : 1006
    },
    "applicableConfigs" : [
      "main", "release/5.10", "release/5.9"
    ],
    "issueUrl" : "https://github.com/apple/swift/issues/57045"
  },
  {
    "path" : "*\/MovieSwift\/MovieSwift\/Shared\/flux\/models\/Movie.swift",
    "modification" : "concurrent-1864",
    "issueDetail" : {
      "kind" : "cursorInfo",
      "offset" : 1008
    },
    "applicableConfigs" : [
      "main", "release/5.10", "release/5.9"
    ],
    "issueUrl" : "https://github.com/apple/swift/issues/57045"
  },
    {
    "path" : "*\/MovieSwift\/MovieSwift\/Shared\/flux\/models\/Movie.swift",
    "modification" : "concurrent-336",
    "issueDetail" : {
      "kind" : "codeComplete",
      "offset" : 263
    },
    "applicableConfigs" : [
      "main", "release/5.10", "release/5.9"
    ],
    "issueUrl" : "https://github.com/apple/swift/issues/57045"
  },
  {
    "path" : "*\/MovieSwift\/MovieSwift\/Shared\/flux\/models\/Movie.swift",
    "modification" : "concurrent-486",
    "issueDetail" : {
      "kind" : "codeComplete",
      "offset" : 301
    },
    "applicableConfigs" : [
      "main", "release/5.10", "release/5.9"
    ],
    "issueUrl" : "https://github.com/apple/swift/issues/57045"
  },
  {
    "path" : "*\/MovieSwift\/MovieSwift\/Shared\/flux\/models\/Movie.swift",
    "modification" : "concurrent-492",
    "issueDetail" : {
      "kind" : "codeComplete",
      "offset" : 307
    },
    "applicableConfigs" : [
      "main", "release/5.10", "release/5.9"
    ],
    "issueUrl" : "https://github.com/apple/swift/issues/57045"
  },
  {
    "path" : "*\/MovieSwift\/MovieSwift\/Shared\/flux\/models\/Movie.swift",
    "modification" : "concurrent-612",
    "issueDetail" : {
      "kind" : "codeComplete",
      "offset" : 316
    },
    "applicableConfigs" : [
      "main", "release/5.10", "release/5.9"
    ],
    "issueUrl" : "https://github.com/apple/swift/issues/57045"
  },
  {
    "path" : "*\/MovieSwift\/MovieSwift\/Shared\/flux\/models\/Movie.swift",
    "modification" : "concurrent-1878",
    "issueDetail" : {
      "kind" : "codeComplete",
      "offset" : 1026
    },
    "applicableConfigs" : [
      "main", "release/5.10", "release/5.9"
    ],
    "issueUrl" : "https://github.com/apple/swift/issues/57045"
  },
  {
    "path" : "*\/MovieSwift\/MovieSwift\/Shared\/flux\/models\/Movie.swift",
    "modification" : "concurrent-1888",
    "issueDetail" : {
      "kind" : "codeComplete",
      "offset" : 1036
    },
    "applicableConfigs" : [
      "main", "release/5.10", "release/5.9"
    ],
    "issueUrl" : "https://github.com/apple/swift/issues/57045"
  },
  {
    "path" : "*\/MovieSwift\/MovieSwift\/Shared\/flux\/models\/Movie.swift",
    "modification" : "concurrent-1896",
    "issueDetail" : {
      "kind" : "codeComplete",
      "offset" : 1044
    },
    "applicableConfigs" : [
      "main", "release/5.10", "release/5.9"
    ],
    "issueUrl" : "https://github.com/apple/swift/issues/57045"
  },
  {
    "path" : "*\/MovieSwift\/MovieSwift\/Shared\/flux\/models\/Movie.swift",
    "modification" : "concurrent-1897",
    "issueDetail" : {
      "kind" : "codeComplete",
      "offset" : 1045
    },
    "applicableConfigs" : [
      "main", "release/5.10", "release/5.9"
    ],
    "issueUrl" : "https://github.com/apple/swift/issues/57045"
  },
  {
    "path" : "*\/ACHNBrowserUI\/ACHNBrowserUI\/ACHNBrowserUI\/views\/userLists\/UserListDetailView.swift",
    "issueDetail" : {
      "kind" : "codeComplete",
      "offset" : 724
    },
    "applicableConfigs" : [
      "main", "release/5.10", "release/5.9"
    ],
    "issueUrl" : "https://github.com/apple/swift/issues/57237"
  },
  {
    "path" : "*\/ACHNBrowserUI\/ACHNBrowserUI\/ACHNBrowserUI\/views\/todayDashboard\/TodayView.swift",
    "modification" : "unmodified",
    "issueDetail" : {
      "kind" : "codeComplete",
      "offset" : 2745
    },
    "applicableConfigs" : [
      "release/5.9"
    ],
    "issueUrl" : "https://github.com/apple/swift/issues/57439"
  },
  {
    "path" : "*\/ACHNBrowserUI\/ACHNBrowserUI\/ACHNBrowserUI\/packages\/Backend\/Sources\/Backend\/services\/NotificationsManager.swift",
    "modification" : "unmodified",
    "issueDetail" : {
      "kind" : "codeComplete",
      "offset" : 1890
    },
    "applicableConfigs" : [
      "release/5.9"
    ],
    "issueUrl" : "https://github.com/apple/swift/issues/58274"
  },
  {
    "path" : "*\/ACHNBrowserUI\/ACHNBrowserUI\/ACHNBrowserUI\/viewModels\/CategoriesSearchViewModel.swift",
    "modification" : "unmodified",
    "issueDetail" : {
      "kind" : "codeComplete",
      "offset" : 754
    },
    "applicableConfigs" : [
      "main", "release/5.10", "release/5.9"
    ],
    "issueUrl" : "https://github.com/apple/swift/issues/58275"
  },
  {
    "path" : "*\/ACHNBrowserUI\/ACHNBrowserUI\/ACHNBrowserUI\/viewModels\/ItemsViewModel.swift",
    "modification" : "unmodified",
    "issueDetail" : {
      "kind" : "codeComplete",
      "offset" : 2140
    },
    "applicableConfigs" : [
      "main", "release/5.10", "release/5.9"
    ],
    "issueUrl" : "https://github.com/apple/swift/issues/58275"
  },
  {
    "path" : "*\/ACHNBrowserUI\/ACHNBrowserUI\/ACHNBrowserUI\/viewModels\/VillagersViewModel.swift",
    "modification" : "unmodified",
    "issueDetail" : {
      "kind" : "codeComplete",
      "offset" : 1132
    },
    "applicableConfigs" : [
      "main", "release/5.10", "release/5.9"
    ],
    "issueUrl" : "https://github.com/apple/swift/issues/58275"
  },
  {
    "path" : "*\/ACHNBrowserUI\/ACHNBrowserUI\/ACHNBrowserUI\/viewModels\/VillagersViewModel.swift",
    "modification" : "unmodified",
    "issueDetail" : {
      "kind" : "codeComplete",
      "offset" : 1823
    },
    "applicableConfigs" : [
      "main", "release/5.10", "release/5.9"
    ],
    "issueUrl" : "https://github.com/apple/swift/issues/58275"
  },
  {
    "path" : "*\/MovieSwift\/MovieSwift\/Packages\/UI\/Sources\/UI\/fields\/SearchTextObservable.swift",
    "modification" : "unmodified",
    "issueDetail" : {
      "kind" : "codeComplete",
      "offset" : 976
    },
    "applicableConfigs" : [
      "main", "release/5.10", "release/5.9"
    ],
    "issueUrl" : "https://github.com/apple/swift/issues/58275"
  },
  {
    "path" : "*\/ACHNBrowserUI\/ACHNBrowserUI\/ACHNBrowserUI\/views\/todayDashboard\/TodayView.swift",
    "modification" : "unmodified",
    "issueDetail" : {
      "kind" : "codeComplete",
      "offset" : 1517
    },
    "applicableConfigs" : [
      "main", "release/5.10", "release/5.9"
    ],
    "issueUrl" : "https://github.com/apple/swift/issues/58276"
  },
  {
    "path" : "*\/ACHNBrowserUI\/ACHNBrowserUI\/ACHNBrowserUI\/views\/settings\/SettingsView.swift",
    "modification" : "unmodified",
    "issueDetail" : {
      "kind" : "codeComplete",
      "offset" : 2373
    },
    "applicableConfigs" : [
      "release/5.9"
    ],
    "issueUrl" : "https://github.com/apple/swift/issues/58316"
  },
  {
    "path" : "*\/ACHNBrowserUI\/ACHNBrowserUI\/ACHNBrowserUI\/views\/turnips\/charts\/TurnipsChart.swift",
    "modification" : "insideOut-171",
    "issueDetail" : {
      "kind" : "codeComplete",
      "offset" : 125
    },
    "applicableConfigs" : [
      "main", "release/5.10", "release/5.9"
    ],
    "issueUrl" : "https://github.com/apple/swift/issues/60192"
  },
  {
    "path" : "*\/ACHNBrowserUI\/ACHNBrowserUI\/ACHNBrowserUI\/views\/turnips\/charts\/TurnipsChart.swift",
    "modification" : "insideOut-171",
    "issueDetail" : {
      "kind" : "typeContextInfo",
      "offset" : 125
    },
    "applicableConfigs" : [
      "main", "release/5.10", "release/5.9"
    ],
    "issueUrl" : "https://github.com/apple/swift/issues/60192"
  },
  {
    "path" : "*\/ACHNBrowserUI\/ACHNBrowserUI\/ACHNBrowserUI\/views\/turnips\/charts\/TurnipsChart.swift",
    "modification" : "insideOut-177",
    "issueDetail" : {
      "kind" : "cursorInfo",
      "offset" : 125
    },
    "applicableConfigs" : [
      "main", "release/5.10", "release/5.9"
    ],
    "issueUrl" : "https://github.com/apple/swift/issues/60192"
  },
  {
    "path" : "*\/ACHNBrowserUI\/ACHNBrowserUI\/ACHNBrowserUI\/views\/turnips\/charts\/TurnipsChart.swift",
    "modification" : "insideOut-177",
    "issueDetail" : {
      "kind" : "codeComplete",
      "offset" : 131
    },
    "applicableConfigs" : [
      "main", "release/5.10", "release/5.9"
    ],
    "issueUrl" : "https://github.com/apple/swift/issues/60192"
  },
  {
    "path" : "*\/ACHNBrowserUI\/ACHNBrowserUI\/ACHNBrowserUI\/views\/turnips\/charts\/TurnipsChart.swift",
    "modification" : "insideOut-188",
    "issueDetail" : {
      "kind" : "codeComplete",
      "offset" : 173
    },
    "applicableConfigs" : [
      "main", "release/5.10", "release/5.9"
    ],
    "issueUrl" : "https://github.com/apple/swift/issues/60192"
  },
  {
    "path" : "*\/ACHNBrowserUI\/ACHNBrowserUI\/ACHNBrowserUI\/extensions\/Path.swift",
    "modification" : "insideOut-907",
    "issueDetail" : {
      "kind" : "codeComplete",
      "offset" : 904
    },
    "applicableConfigs" : [
      "release/5.9"
    ],
    "issueUrl" : "https://github.com/apple/swift/issues/60192"
  },
  {
    "path" : "*\/ACHNBrowserUI\/ACHNBrowserUI\/ACHNBrowserUI\/extensions\/Path.swift",
    "modification" : "insideOut-915",
    "issueDetail" : {
      "kind" : "codeComplete",
      "offset" : 915
    },
    "applicableConfigs" : [
      "main", "release/5.10", "release/5.9"    
    ],
    "issueUrl" : "https://github.com/apple/swift/issues/60192"
  },
  {
    "path" : "*\/ACHNBrowserUI\/ACHNBrowserUI\/ACHNBrowserUI\/viewModels\/ItemsViewModel.swift",
    "modification" : "insideOut-489",
    "issueDetail" : {
      "kind" : "rangeInfo",
      "length" : 16,
      "offset" : 135
    },
    "applicableConfigs" : [
      "release/5.9"
    ],
    "issueUrl" : "https://github.com/apple/swift/issues/60192"
  },
  {
    "path" : "*\/MovieSwift\/MovieSwift\/MovieSwift\/views\/components\/discover\/DraggableCover.swift",
    "modification" : "insideOut-231",
    "issueDetail" : {
      "kind" : "cursorInfo",
      "offset" : 73
    },
    "applicableConfigs" : [
      "release/5.9"
    ],
    "issueUrl" : "https://github.com/apple/swift/issues/60192"
  },
  {
    "path" : "*\/MovieSwift\/MovieSwift\/MovieSwift\/views\/components\/discover\/DraggableCover.swift",
    "modification" : "insideOut-231",
    "issueDetail" : {
      "kind" : "rangeInfo",
      "length" : 5,
      "offset" : 72
    },
    "applicableConfigs" : [
      "main", "release/5.10", "release/5.9"
    ],
    "issueUrl" : "https://github.com/apple/swift/issues/60192"
  },
  {
    "path" : "*\/MovieSwift\/MovieSwift\/MovieSwift\/views\/components\/discover\/DraggableCover.swift",
    "modification" : "insideOut-242",
    "issueDetail" : {
      "kind" : "cursorInfo",
      "offset" : 77
    },
    "applicableConfigs" : [
      "main", "release/5.10", "release/5.9"
    ],
    "issueUrl" : "https://github.com/apple/swift/issues/60192"
  },
  {
    "path" : "*\/MovieSwift\/MovieSwift\/MovieSwift\/views\/components\/discover\/DraggableCover.swift",
    "modification" : "insideOut-242",
    "issueDetail" : {
      "kind" : "rangeInfo",
      "length" : 165,
      "offset" : 77
    },
    "applicableConfigs" : [
      "main", "release/5.10", "release/5.9"
    ],
    "issueUrl" : "https://github.com/apple/swift/issues/60192"
  },
  {
    "path" : "*\/ACHNBrowserUI\/ACHNBrowserUI\/ACHNBrowserUI\/extensions\/Path.swift",
    "modification" : "insideOut-893",
    "issueDetail" : {
      "kind" : "codeComplete",
      "offset" : 884
    },
    "applicableConfigs" : [
      "release/5.9"
    ],
    "issueUrl" : "https://github.com/apple/swift/issues/60192"
  },
  {
    "path" : "*\/ACHNBrowserUI\/ACHNBrowserUI\/ACHNBrowserUI\/extensions\/Path.swift",
    "modification" : "insideOut-895",
    "issueDetail" : {
      "kind" : "codeComplete",
      "offset" : 889
    },
    "applicableConfigs" : [
      "release/5.9"
    ],
    "issueUrl" : "https://github.com/apple/swift/issues/60192"
  },
  {
    "path" : "*\/ACHNBrowserUI\/ACHNBrowserUI\/ACHNBrowserUI\/views\/turnips\/charts\/TurnipsChart.swift",
    "modification" : "insideOut-177",
    "issueDetail" : {
      "kind" : "conformingMethodList",
      "offset" : 131
    },
    "applicableConfigs" : [
      "main", "release/5.10", "release/5.9"
    ],
    "issueUrl" : "https://github.com/apple/swift/issues/60192"
  },
  {
    "path" : "*\/MovieSwift\/MovieSwift\/MovieSwift\/views\/components\/discover\/DraggableCover.swift",
    "modification" : "insideOut-258",
    "issueDetail" : {
      "kind" : "cursorInfo",
      "offset" : 244
    },
    "applicableConfigs" : [
      "release/5.9"
    ],
    "issueUrl" : "https://github.com/apple/swift/issues/60192"
  },
  {
    "path" : "*\/ACHNBrowserUI\/ACHNBrowserUI\/ACHNBrowserUI\/views\/categories\/CategoriesView.swift",
    "modification" : "unmodified",
    "issueDetail" : {
      "kind" : "codeComplete",
      "offset" : 602
    },
    "applicableConfigs" : [
      "main", "release/5.10", "release/5.9"
    ],
    "issueUrl" : "https://github.com/apple/swift/issues/61488"
  },
  {
    "path" : "*\/DNS\/Tests\/DNSTests\/DNSTests.swift",
    "modification" : "unmodified",
    "issueDetail" : {
      "kind" : "codeComplete",
      "offset" : 15
    },
    "applicableConfigs" : [
      "main", "release/5.10", "release/5.9"
    ],
    "issueUrl" : "https://github.com/apple/swift/issues/63049"
  },
  {
    "path" : "*\/DNS\/Tests\/DNSTests\/FuzzTests.swift",
    "modification" : "unmodified",
    "issueDetail" : {
      "kind" : "codeComplete",
      "offset" : 15
    },
    "applicableConfigs" : [
      "main", "release/5.10", "release/5.9"
    ],
    "issueUrl" : "https://github.com/apple/swift/issues/63049"
  },
  {
    "path" : "*\/DNS\/Tests\/DNSTests\/IPTests.swift",
    "modification" : "unmodified",
    "issueDetail" : {
      "kind" : "codeComplete",
      "offset" : 15
    },
    "applicableConfigs" : [
      "main", "release/5.10", "release/5.9"
    ],
    "issueUrl" : "https://github.com/apple/swift/issues/63049"
  },
  {
    "path" : "*\/ACHNBrowserUI\/ACHNBrowserUI\/ACHNBrowserUI\/views\/turnips\/charts\/TurnipsChartValuesView.swift",
    "modification" : "concurrent-741",
    "issueDetail" : {
      "kind" : "semanticRefactoring",
      "refactoring" : "Local Rename",
      "offset" : 734
    },
    "applicableConfigs" : [
      "main", "release/5.10", "release/5.9"
    ],
    "issueUrl" : "https://github.com/apple/swift/issues/63610"
  },
  {
    "path" : "*\/DNS\/Tests\/DNSTests\/FuzzTests.swift",
    "modification" : "concurrent-183",
    "issueDetail" : {
      "kind" : "semanticRefactoring",
      "refactoring" : "Local Rename",
      "offset" : 179
    },
    "applicableConfigs" : [
      "main", "release/5.10", "release/5.9"
    ],
    "issueUrl" : "https://github.com/apple/swift/issues/63611"
  },
  {
    "path" : "*\/Dollar\/Sources\/Dollar.swift",
    "modification" : "unmodified",
    "issueDetail" : {
      "kind" : "semanticRefactoring",
      "refactoring" : "Local Rename",
      "offset" : 43395
    },
    "applicableConfigs" : [
      "main", "release/5.10", "release/5.9"
    ],
    "issueUrl" : "https://github.com/apple/swift/issues/63611"
  },
  {
    "path" : "*\/Dollar\/Sources\/Dollar.swift",
    "modification" : "unmodified",
    "issueDetail" : {
      "kind" : "semanticRefactoring",
      "refactoring" : "Local Rename",
      "offset" : 43490
    },
    "applicableConfigs" : [
      "main", "release/5.10", "release/5.9"
    ],
    "issueUrl" : "https://github.com/apple/swift/issues/63611"
  },
  {
    "path" : "*\/Result\/Result\/Result.swift",
    "modification" : "unmodified",
    "issueDetail" : {
      "kind" : "semanticRefactoring",
      "refactoring" : "Local Rename",
      "offset" : 6494
    },
    "applicableConfigs" : [
      "main", "release/5.10", "release/5.9"
    ],
    "issueUrl" : "https://github.com/apple/swift/issues/63611"
  },
  {
    "path" : "*\/Result\/Result\/Result.swift",
    "modification" : "unmodified",
    "issueDetail" : {
      "kind" : "semanticRefactoring",
      "refactoring" : "Local Rename",
      "offset" : 6517
    },
    "applicableConfigs" : [
      "main", "release/5.10", "release/5.9"
    ],
    "issueUrl" : "https://github.com/apple/swift/issues/63611"
  },
  {
    "path" : "*\/Result\/Result\/Result.swift",
    "modification" : "unmodified",
    "issueDetail" : {
      "kind" : "semanticRefactoring",
      "refactoring" : "Local Rename",
      "offset" : 6581
    },
    "applicableConfigs" : [
      "main", "release/5.10", "release/5.9"
    ],
    "issueUrl" : "https://github.com/apple/swift/issues/63611"
  },
  {
    "path" : "*\/Result\/Result\/Result.swift",
    "modification" : "unmodified",
    "issueDetail" : {
      "kind" : "semanticRefactoring",
      "refactoring" : "Local Rename",
      "offset" : 6604
    },
    "applicableConfigs" : [
      "main", "release/5.10", "release/5.9"
    ],
    "issueUrl" : "https://github.com/apple/swift/issues/63611"
  },
  {
    "path" : "*\/ACHNBrowserUI\/ACHNBrowserUI\/ACHNBrowserUI\/packages\/Backend\/Sources\/Backend\/extensions\/Array.swift",
    "modification" : "concurrent-492",
    "issueDetail" : {
      "kind" : "semanticRefactoring",
      "refactoring" : "Local Rename",
      "offset" : 489
    },
    "applicableConfigs" : [
      "main", "release/5.10", "release/5.9"
    ],
    "issueUrl" : "https://github.com/apple/swift/issues/64512"
  },
  {
    "path" : "*\/ACHNBrowserUI\/ACHNBrowserUI\/ACHNBrowserUI\/packages\/Backend\/Sources\/Backend\/extensions\/Array.swift",
    "modification" : "concurrent-605",
    "issueDetail" : {
      "kind" : "semanticRefactoring",
      "refactoring" : "Local Rename",
      "offset" : 602
    },
    "applicableConfigs" : [
      "main", "release/5.10", "release/5.9"
    ],
    "issueUrl" : "https://github.com/apple/swift/issues/64512"
  },
  {
    "path" : "*\/ACHNBrowserUI\/ACHNBrowserUI\/ACHNBrowserUI\/views\/turnips\/charts\/TurnipsChartGrid.swift",
    "modification" : "concurrent-1130",
    "issueDetail" : {
      "kind" : "semanticRefactoring",
      "refactoring" : "Local Rename",
      "offset" : 1127
    },
    "applicableConfigs" : [
      "main", "release/5.10", "release/5.9"
    ],
    "issueUrl" : "https://github.com/apple/swift/issues/64512"
  },
  {
    "path" : "*\/ACHNBrowserUI\/ACHNBrowserUI\/ACHNBrowserUI\/views\/turnips\/charts\/TurnipsChartGrid.swift",
    "modification" : "concurrent-1241",
    "issueDetail" : {
      "kind" : "semanticRefactoring",
      "refactoring" : "Local Rename",
      "offset" : 1229
    },
    "applicableConfigs" : [
      "main", "release/5.10", "release/5.9"
    ],
    "issueUrl" : "https://github.com/apple/swift/issues/64512"
  },
  {
    "path" : "*\/ACHNBrowserUI\/ACHNBrowserUI\/ACHNBrowserUI\/views\/turnips\/charts\/TurnipsChartValuesView.swift",
    "modification" : "concurrent-678",
    "issueDetail" : {
      "kind" : "semanticRefactoring",
      "refactoring" : "Local Rename",
      "offset" : 506
    },
    "applicableConfigs" : [
      "release/5.9"
    ],
    "issueUrl" : "https://github.com/apple/swift/issues/64512"
  },
  {
    "path" : "*\/MovieSwift\/MovieSwift\/Packages\/Backend\/Sources\/Backend\/utils\/ImageLoader.swift",
    "modification" : "concurrent-1203",
    "issueDetail" : {
      "kind" : "semanticRefactoring",
      "refactoring" : "Local Rename",
      "offset" : 1198
    },
    "applicableConfigs" : [
      "main", "release/5.10", "release/5.9"
    ],
    "issueUrl" : "https://github.com/apple/swift/issues/64512"
  },
  {
    "path" : "*\/MovieSwift\/MovieSwift\/MovieSwift\/views\/components\/peopleDetail\/PeopleDetail.swift",
    "modification" : "concurrent-1523",
    "issueDetail" : {
      "kind" : "semanticRefactoring",
      "refactoring" : "Local Rename",
      "offset" : 1283
    },
    "applicableConfigs" : [
      "main", "release/5.10", "release/5.9"
    ],
    "issueUrl" : "https://github.com/apple/swift/issues/64512"
  },
  {
    "path" : "*\/MovieSwift\/MovieSwift\/Shared\/extensions\/Font.swift",
    "modification" : "concurrent-596",
    "issueDetail" : {
      "kind" : "semanticRefactoring",
      "refactoring" : "Local Rename",
      "offset" : 593
    },
    "applicableConfigs" : [
      "main", "release/5.10", "release/5.9"
    ],
    "issueUrl" : "https://github.com/apple/swift/issues/64512"
  },
  {
    "path" : "*\/MovieSwift\/MovieSwift\/Shared\/views\/modifiers\/PosterStyle.swift",
    "modification" : "concurrent-552",
    "issueDetail" : {
      "kind" : "semanticRefactoring",
      "refactoring" : "Local Rename",
      "offset" : 547
    },
    "applicableConfigs" : [
      "main", "release/5.10", "release/5.9"
    ],
    "issueUrl" : "https://github.com/apple/swift/issues/64512"
  },
  {
    "path" : "*\/Result\/Result\/Result.swift",
    "modification" : "unmodified",
    "issueDetail" : {
      "kind" : "semanticRefactoring",
      "refactoring" : "Local Rename",
      "offset" : 6501
    },
    "applicableConfigs" : [
      "main", "release/5.10", "release/5.9"
    ],
    "issueUrl" : "https://github.com/apple/swift/issues/64512"
  },
  {
    "path" : "*\/Result\/Result\/Result.swift",
    "modification" : "unmodified",
    "issueDetail" : {
      "kind" : "semanticRefactoring",
      "refactoring" : "Local Rename",
      "offset" : 6525
    },
    "applicableConfigs" : [
      "main", "release/5.10", "release/5.9"
    ],
    "issueUrl" : "https://github.com/apple/swift/issues/64512"
  },
  {
    "path" : "*\/Result\/Result\/Result.swift",
    "modification" : "unmodified",
    "issueDetail" : {
      "kind" : "semanticRefactoring",
      "refactoring" : "Local Rename",
      "offset" : 6550
    },
    "applicableConfigs" : [
      "main", "release/5.10", "release/5.9"
    ],
    "issueUrl" : "https://github.com/apple/swift/issues/64512"
  },
  {
    "path" : "*\/Result\/Result\/Result.swift",
    "modification" : "unmodified",
    "issueDetail" : {
      "kind" : "semanticRefactoring",
      "refactoring" : "Local Rename",
      "offset" : 6558
    },
    "applicableConfigs" : [
      "main", "release/5.10", "release/5.9"
    ],
    "issueUrl" : "https://github.com/apple/swift/issues/64512"
  },
  {
    "path" : "*\/Result\/Result\/Result.swift",
    "modification" : "unmodified",
    "issueDetail" : {
      "kind" : "semanticRefactoring",
      "refactoring" : "Local Rename",
      "offset" : 6588
    },
    "applicableConfigs" : [
      "main", "release/5.10", "release/5.9"
    ],
    "issueUrl" : "https://github.com/apple/swift/issues/64512"
  },
  {
    "path" : "*\/Result\/Result\/Result.swift",
    "modification" : "unmodified",
    "issueDetail" : {
      "kind" : "semanticRefactoring",
      "refactoring" : "Local Rename",
      "offset" : 6612
    },
    "applicableConfigs" : [
      "main", "release/5.10", "release/5.9"
    ],
    "issueUrl" : "https://github.com/apple/swift/issues/64512"
  },
  {
    "path" : "*\/Result\/Result\/Result.swift",
    "modification" : "unmodified",
    "issueDetail" : {
      "kind" : "semanticRefactoring",
      "refactoring" : "Local Rename",
      "offset" : 6637
    },
    "applicableConfigs" : [
      "main", "release/5.10", "release/5.9"
    ],
    "issueUrl" : "https://github.com/apple/swift/issues/64512"
  },
  {
    "path" : "*\/Result\/Result\/Result.swift",
    "modification" : "unmodified",
    "issueDetail" : {
      "kind" : "semanticRefactoring",
      "refactoring" : "Local Rename",
      "offset" : 6645
    },
    "applicableConfigs" : [
      "main", "release/5.10", "release/5.9"
    ],
    "issueUrl" : "https://github.com/apple/swift/issues/64512"
  },
  {
    "path" : "*\/Result\/Result\/Result.swift",
    "modification" : "unmodified",
    "issueDetail" : {
      "kind" : "semanticRefactoring",
      "refactoring" : "Local Rename",
      "offset" : 6989
    },
    "applicableConfigs" : [
      "main", "release/5.10", "release/5.9"
    ],
    "issueUrl" : "https://github.com/apple/swift/issues/64512"
  },
  {
    "path" : "*\/Result\/Result\/Result.swift",
    "modification" : "unmodified",
    "issueDetail" : {
      "kind" : "semanticRefactoring",
      "refactoring" : "Local Rename",
      "offset" : 6997
    },
    "applicableConfigs" : [
      "main", "release/5.10", "release/5.9"
    ],
    "issueUrl" : "https://github.com/apple/swift/issues/64512"
  },
  {
    "path" : "*\/DNS\/Tests\/DNSTests\/FuzzTests.swift",
    "modification" : "unmodified",
    "issueDetail" : {
      "kind" : "semanticRefactoring",
      "refactoring" : "Local Rename",
      "offset" : 165
    },
    "applicableConfigs" : [
      "main", "release/5.10", "release/5.9"
    ],
    "issueUrl" : "https://github.com/apple/swift/issues/64512"
  },
  {
    "path" : "*\/DNS\/Tests\/DNSTests\/FuzzTests.swift",
    "modification" : "concurrent-412",
    "issueDetail" : {
      "kind" : "semanticRefactoring",
      "refactoring" : "Local Rename",
      "offset" : 165
    },
    "applicableConfigs" : [
      "main", "release/5.10", "release/5.9"
    ],
    "issueUrl" : "https://github.com/apple/swift/issues/64512"
  },
  {
    "path" : "*\/swift-power-assert\/Sources\/StringWidth\/StringWidth.swift",
    "modification" : "concurrent-438",
    "issueDetail" : {
      "kind" : "semanticRefactoring",
      "refactoring" : "Local Rename",
      "offset" : 433
    },
    "applicableConfigs" : [
      "main", "release/5.10", "release/5.9"
    ],
    "issueUrl" : "https://github.com/apple/swift/issues/64512"
  },
  {
    "path" : "*\/swift-power-assert\/Sources\/PowerAssertPlugin\/PowerAssertMacro.swift",
    "modification" : "concurrent-790",
    "issueDetail" : {
      "kind" : "semanticRefactoring",
      "refactoring" : "Local Rename",
      "offset" : 328
    },
    "applicableConfigs" : [
      "main", "release/5.10", "release/5.9"
    ],
    "issueUrl" : "https://github.com/apple/swift/issues/64512"
  },
  {
    "path" : "*\/swift-power-assert\/Sources\/PowerAssert\/PowerAssert.swift",
    "modification" : "unmodified",
    "issueDetail" : {
      "kind" : "semanticRefactoring",
      "refactoring" : "Local Rename",
      "offset" : 4181
    },
    "applicableConfigs" : [
      "main", "release/5.10", "release/5.9"
    ],
    "issueUrl" : "https://github.com/apple/swift/issues/64512"
  },
  {
    "path" : "*\/swift-power-assert\/Sources\/PowerAssert\/PowerAssert.swift",
    "modification" : "unmodified",
    "issueDetail" : {
      "kind" : "semanticRefactoring",
      "refactoring" : "Local Rename",
      "offset" : 4259
    },
    "applicableConfigs" : [
      "main", "release/5.10", "release/5.9"
    ],
    "issueUrl" : "https://github.com/apple/swift/issues/64512"
  },
  {
    "path" : "*\/MovieSwift\/MovieSwift\/MovieSwift\/views\/components\/custom list\/CustomListDetail.swift",
    "modification" : "unmodified",
    "issueDetail" : {
      "kind" : "codeComplete",
      "offset" : 4527
    },
    "applicableConfigs" : [
      "release/5.9"
    ],
    "issueUrl" : "https://github.com/apple/swift/issues/65816"
  },
  {
    "path" : "*\/ACHNBrowserUI\/ACHNBrowserUI\/ACHNBrowserUI\/views\/collection\/CollectionListView.swift",
    "modification" : "unmodified",
    "issueDetail" : {
      "kind" : "codeComplete",
      "offset" : 1478
    },
    "applicableConfigs" : [
      "release/5.9"
    ],
    "issueUrl" : "https://github.com/apple/swift/issues/65895"
  },
  {
    "path" : "*\/ACHNBrowserUI\/ACHNBrowserUI\/ACHNBrowserUI\/views\/collection\/CollectionListView.swift",
    "modification" : "unmodified",
    "issueDetail" : {
      "kind" : "codeComplete",
      "offset" : 1479
    },
    "applicableConfigs" : [
      "release/5.9"
    ],
    "issueUrl" : "https://github.com/apple/swift/issues/65895"
  },
  {
    "path" : "*\/ACHNBrowserUI\/ACHNBrowserUI\/ACHNBrowserUI\/views\/collection\/CollectionListView.swift",
    "modification" : "unmodified",
    "issueDetail" : {
      "kind" : "codeComplete",
      "offset" : 1492
    },
    "applicableConfigs" : [
      "main", "release/5.10", "release/5.9"
    ],
    "issueUrl" : "https://github.com/apple/swift/issues/65895"
  },
  {
    "path" : "*\/ACHNBrowserUI\/ACHNBrowserUI\/ACHNBrowserUI\/views\/collection\/CollectionListView.swift",
    "modification" : "unmodified",
    "issueDetail" : {
      "kind" : "codeComplete",
      "offset" : 1503
    },
    "applicableConfigs" : [
      "main", "release/5.10", "release/5.9"
    ],
    "issueUrl" : "https://github.com/apple/swift/issues/65895"
  },
  {
    "path" : "*\/ACHNBrowserUI\/ACHNBrowserUI\/ACHNBrowserUI\/views\/collection\/CollectionListView.swift",
    "modification" : "unmodified",
    "issueDetail" : {
      "kind" : "codeComplete",
      "offset" : 1512
    },
    "applicableConfigs" : [
      "main", "release/5.10", "release/5.9"
    ],
    "issueUrl" : "https://github.com/apple/swift/issues/65895"
  },
  {
    "path" : "*\/ACHNBrowserUI\/ACHNBrowserUI\/ACHNBrowserUI\/views\/collection\/CollectionListView.swift",
    "modification" : "unmodified",
    "issueDetail" : {
      "kind" : "codeComplete",
      "offset" : 1858
    },
    "applicableConfigs" : [
      "release/5.9"
    ],
    "issueUrl" : "https://github.com/apple/swift/issues/65895"
  },
  {
    "path" : "*\/ACHNBrowserUI\/ACHNBrowserUI\/ACHNBrowserUI\/views\/collection\/CollectionListView.swift",
    "modification" : "unmodified",
    "issueDetail" : {
      "kind" : "codeComplete",
      "offset" : 1859
    },
    "applicableConfigs" : [
      "release/5.9"
    ],
    "issueUrl" : "https://github.com/apple/swift/issues/65895"
  },
  {
    "path" : "*\/ACHNBrowserUI\/ACHNBrowserUI\/ACHNBrowserUI\/views\/collection\/CollectionListView.swift",
    "modification" : "unmodified",
    "issueDetail" : {
      "kind" : "typeContextInfo",
      "offset" : 1478
    },
    "applicableConfigs" : [
      "release/5.9"
    ],
    "issueUrl" : "https://github.com/apple/swift/issues/65895"
  },
  {
    "path" : "*\/ACHNBrowserUI\/ACHNBrowserUI\/ACHNBrowserUI\/views\/collection\/CollectionListView.swift",
    "modification" : "unmodified",
    "issueDetail" : {
      "kind" : "typeContextInfo",
      "offset" : 1479
    },
    "applicableConfigs" : [
      "release/5.9"
    ],
    "issueUrl" : "https://github.com/apple/swift/issues/65895"
  },
  {
    "path" : "*\/ACHNBrowserUI\/ACHNBrowserUI\/ACHNBrowserUI\/views\/collection\/CollectionListView.swift",
    "modification" : "unmodified",
    "issueDetail" : {
      "kind" : "typeContextInfo",
      "offset" : 1492
    },
    "applicableConfigs" : [
      "main", "release/5.10", "release/5.9"
    ],
    "issueUrl" : "https://github.com/apple/swift/issues/65895"
  },
  {
    "path" : "*\/ACHNBrowserUI\/ACHNBrowserUI\/ACHNBrowserUI\/views\/collection\/CollectionListView.swift",
    "modification" : "unmodified",
    "issueDetail" : {
      "kind" : "typeContextInfo",
      "offset" : 1858
    },
    "applicableConfigs" : [
      "release/5.9"
    ],
    "issueUrl" : "https://github.com/apple/swift/issues/65895"
  },
  {
    "path" : "*\/ACHNBrowserUI\/ACHNBrowserUI\/ACHNBrowserUI\/views\/collection\/CollectionListView.swift",
    "modification" : "unmodified",
    "issueDetail" : {
      "kind" : "typeContextInfo",
      "offset" : 1859
    },
    "applicableConfigs" : [
      "release/5.9"
    ],
    "issueUrl" : "https://github.com/apple/swift/issues/65895"
  },
  {
  "path" : "*\/ACHNBrowserUI\/ACHNBrowserUI\/ACHNBrowserUI\/views\/todayDashboard\/TodayTurnipSection.swift",
    "modification" : "unmodified",
    "issueDetail" : {
      "kind" : "codeComplete",
      "offset" : 1790
    },
    "applicableConfigs" : [
      "release/5.9"
    ],
    "issueUrl" : "https://github.com/apple/swift/issues/65895"
  },
  {
    "path" : "*\/ACHNBrowserUI\/ACHNBrowserUI\/ACHNBrowserUI\/views\/todayDashboard\/TodayTurnipSection.swift",
    "modification" : "unmodified",
    "issueDetail" : {
      "kind" : "codeComplete",
      "offset" : 1830
    },
    "applicableConfigs" : [
      "release/5.9"
    ],
    "issueUrl" : "https://github.com/apple/swift/issues/65895"
  },
  {
    "path" : "*\/ACHNBrowserUI\/ACHNBrowserUI\/ACHNBrowserUI\/views\/todayDashboard\/TodayTurnipSection.swift",
    "modification" : "unmodified",
    "issueDetail" : {
      "kind" : "codeComplete",
      "offset" : 1583
    },
    "applicableConfigs" : [
      "main", "release/5.10", "release/5.9"
    ],
    "issueUrl" : "https://github.com/apple/swift/issues/65895"
  },
  {
    "path" : "*\/ACHNBrowserUI\/ACHNBrowserUI\/ACHNBrowserUI\/views\/todayDashboard\/TodayTurnipSection.swift",
    "modification" : "unmodified",
    "issueDetail" : {
      "kind" : "typeContextInfo",
      "offset" : 1583
    },
    "applicableConfigs" : [
      "main", "release/5.10", "release/5.9"
    ],
    "issueUrl" : "https://github.com/apple/swift/issues/65895"
  },
  {
    "path" : "*\/ACHNBrowserUI\/ACHNBrowserUI\/ACHNBrowserUI\/views\/todayDashboard\/TodayTurnipSection.swift",
    "modification" : "unmodified",
    "issueDetail" : {
      "kind" : "codeComplete",
      "offset" : 1011
    },
    "applicableConfigs" : [
      "release\/5.9"
    ],
    "issueUrl" : "https://github.com/apple/swift/issues/65895"
  },
  {
    "path" : "*\/swift-power-assert\/Sources\/PowerAssert\/Macros.swift",
    "modification" : "unmodified",
    "issueDetail" : {
      "kind" : "codeComplete",
      "offset" : 743
    },
    "applicableConfigs" : [
      "main", "release/5.10"
    ],
    "issueUrl" : "https://github.com/apple/swift/issues/66923"
  },
  {
    "path" : "*\/swift-power-assert\/Sources\/PowerAssert\/Macros.swift",
    "modification" : "unmodified",
    "issueDetail" : {
      "kind" : "codeComplete",
      "offset" : 1065
    },
    "applicableConfigs" : [
      "main", "release/5.10"
    ],
    "issueUrl" : "https://github.com/apple/swift/issues/66923"
  },
  {
    "path" : "*\/swift-power-assert\/Sources\/PowerAssert\/Macros.swift",
    "modification" : "unmodified",
    "issueDetail" : {
      "kind" : "codeComplete",
      "offset" : 1392
    },
    "applicableConfigs" : [
      "main", "release/5.10"
    ],
    "issueUrl" : "https://github.com/apple/swift/issues/66923"
  },
  {
    "path" : "*\/swift-power-assert\/Sources\/PowerAssert\/PowerAssert.swift",
    "modification" : "unmodified",
    "issueDetail" : {
      "kind" : "codeComplete",
      "offset" : 1792
    },
    "applicableConfigs" : [
      "main", "release/5.10", "release/5.9"
    ],
    "issueUrl" : "https://github.com/apple/swift/issues/66925"
  },
  {
    "path" : "*\/swift-power-assert\/Sources\/PowerAssert\/PowerAssert.swift",
    "modification" : "unmodified",
    "issueDetail" : {
      "kind" : "codeComplete",
      "offset" : 4190
    },
    "applicableConfigs" : [
      "main", "release/5.10", "release/5.9"
    ],
    "issueUrl" : "https://github.com/apple/swift/issues/66926"
  },
  {
    "path" : "*\/ACHNBrowserUI\/ACHNBrowserUI\/ACHNBrowserUI\/views\/collection\/CollectionListView.swift",
    "modification" : "unmodified",
    "issueDetail" : {
      "kind" : "codeComplete",
      "offset" : 1511
    },
    "applicableConfigs" : [
      "main", "release/5.10"
    ],
    "issueUrl" : "https://github.com/apple/swift/issues/67248"
  },
  {
    "path" : "*\/ACHNBrowserUI\/ACHNBrowserUI\/ACHNBrowserUI\/views\/collection\/CollectionListView.swift",
    "modification" : "unmodified",
    "issueDetail" : {
      "kind" : "codeComplete",
      "offset" : 1519
    },
    "applicableConfigs" : [
      "main", "release/5.10"
    ],
    "issueUrl" : "https://github.com/apple/swift/issues/67248"
  },
  {
    "path" : "*\/ACHNBrowserUI\/ACHNBrowserUI\/ACHNBrowserUI\/views\/todayDashboard\/TodayTurnipSection.swift",
    "modification" : "insideOut-743",
    "issueDetail" : {
      "kind" : "codeComplete",
      "offset" : 743
    },
    "applicableConfigs" : [
      "main", "release/5.10"
    ],
    "issueUrl" : "https://github.com/apple/swift/issues/67248"
  },
  {
    "path" : "*\/ACHNBrowserUI\/ACHNBrowserUI\/ACHNBrowserUI\/views\/todayDashboard\/TodayTurnipSection.swift",
    "modification" : "insideOut-743",
    "issueDetail" : {
      "kind" : "conformingMethodList",
      "offset" : 743
    },
    "applicableConfigs" : [
      "main", "release/5.10"
    ],
    "issueUrl" : "https://github.com/apple/swift/issues/67248"
  }, 
  {
    "path" : "*\/ACHNBrowserUI\/ACHNBrowserUI\/ACHNBrowserUI\/views\/todayDashboard\/TodayTurnipSection.swift",
    "modification" : "insideOut-768",
    "issueDetail" : {
      "kind" : "collectExpressionType"
    },
    "applicableConfigs" : [
      "main", "release/5.10"
    ],
    "issueUrl" : "https://github.com/apple/swift/issues/67248"
  },
  {
    "path" : "*\/ACHNBrowserUI\/ACHNBrowserUI\/ACHNBrowserUI\/views\/todayDashboard\/TodayTurnipSection.swift",
    "modification" : "insideOut-772",
    "issueDetail" : {
      "kind" : "cursorInfo",
      "offset" : 25
    },
    "applicableConfigs" : [
      "main", "release/5.10"
    ],
    "issueUrl" : "https://github.com/apple/swift/issues/67248"
  },
  {
    "path" : "*\/ACHNBrowserUI\/ACHNBrowserUI\/ACHNBrowserUI\/views\/todayDashboard\/TodayTurnipSection.swift",
    "modification" : "insideOut-777",
    "issueDetail" : {
      "kind" : "rangeInfo",
      "length" : 85,
      "offset" : 211
    },
    "applicableConfigs" : [
      "main", "release/5.10"
    ],
    "issueUrl" : "https://github.com/apple/swift/issues/67248"
  },
  {
    "path" : "*\/ACHNBrowserUI\/ACHNBrowserUI\/ACHNBrowserUI\/views\/todayDashboard\/TodayTurnipSection.swift",
    "modification" : "insideOut-779",
    "issueDetail" : {
      "kind" : "rangeInfo",
      "length" : 82,
      "offset" : 25
    },
    "applicableConfigs" : [
      "main", "release/5.10"
    ],
    "issueUrl" : "https://github.com/apple/swift/issues/67248"
  },
  {
    "path" : "*\/ACHNBrowserUI\/ACHNBrowserUI\/ACHNBrowserUI\/views\/todayDashboard\/TodayTurnipSection.swift",
    "modification" : "insideOut-787",
    "issueDetail" : {
      "kind" : "cursorInfo",
      "offset" : 0
    },
    "applicableConfigs" : [
      "main", "release/5.10"
    ],
    "issueUrl" : "https://github.com/apple/swift/issues/67248"
  },
  {
    "path" : "*\/ACHNBrowserUI\/ACHNBrowserUI\/ACHNBrowserUI\/views\/todayDashboard\/TodayTurnipSection.swift",
    "modification" : "insideOut-813",
    "issueDetail" : {
      "kind" : "rangeInfo",
      "length" : 133,
      "offset" : 197
    },
    "applicableConfigs" : [
      "main", "release/5.10"
    ],
    "issueUrl" : "https://github.com/apple/swift/issues/67248"
  },
  {
    "path" : "*\/ACHNBrowserUI\/ACHNBrowserUI\/ACHNBrowserUI\/views\/todayDashboard\/TodayTurnipSection.swift",
    "modification" : "insideOut-835",
    "issueDetail" : {
      "kind" : "collectExpressionType"
    },
    "applicableConfigs" : [
      "main", "release/5.10"
    ],
    "issueUrl" : "https://github.com/apple/swift/issues/67248"
  },
  {
    "path" : "*\/ACHNBrowserUI\/ACHNBrowserUI\/ACHNBrowserUI\/views\/todayDashboard\/TodayTurnipSection.swift",
    "modification" : "insideOut-836",
    "issueDetail" : {
      "kind" : "conformingMethodList",
      "offset" : 836
    },
    "applicableConfigs" : [
      "main", "release/5.10"
    ],
    "issueUrl" : "https://github.com/apple/swift/issues/67248"
  },
  {
    "path" : "*\/ACHNBrowserUI\/ACHNBrowserUI\/ACHNBrowserUI\/views\/todayDashboard\/TodayTurnipSection.swift",
    "modification" : "insideOut-1529",
    "issueDetail" : {
      "kind" : "codeComplete",
      "offset" : 1295
    },
    "applicableConfigs" : [
      "main", "release/5.10"
    ],
    "issueUrl" : "https://github.com/apple/swift/issues/67248"
  },
  {
    "path" : "*\/ACHNBrowserUI\/ACHNBrowserUI\/ACHNBrowserUI\/views\/collection\/CollectionListView.swift",
    "modification" : "unmodified",
    "issueDetail" : {
      "kind" : "codeComplete",
      "offset" : 1502
    },
    "applicableConfigs" : [
      "main", "release/5.10"
    ],
    "issueUrl" : "https://github.com/apple/swift/issues/67248"
  },
  {
    "path" : "*\/ACHNBrowserUI\/ACHNBrowserUI\/ACHNBrowserUI\/views\/todayDashboard\/TodayTurnipSection.swift",
    "modification" : "insideOut-860",
    "issueDetail" : {
      "kind" : "rangeInfo",
      "length" : 130,
      "offset" : 9
    },
    "applicableConfigs" : [
      "main", "release/5.10"
    ],
    "issueUrl" : "https://github.com/apple/swift/issues/67248"
  },
  {
    "path" : "*\/ACHNBrowserUI\/ACHNBrowserUI\/ACHNBrowserUI\/views\/userLists\/UserListDetailView.swift",
    "modification" : "unmodified",
    "issueDetail" : {
      "kind" : "codeComplete",
      "offset" : 2922
    },
    "applicableConfigs" : [
      "main", "release/5.10"
    ],
    "issueUrl" : "https://github.com/apple/swift/issues/67248"
  },
  {
    "path" : "*\/ACHNBrowserUI\/ACHNBrowserUI\/ACHNBrowserUI\/views\/userLists\/UserListDetailView.swift",
    "modification" : "unmodified",
    "issueDetail" : {
      "kind" : "codeComplete",
      "offset" : 2939
    },
    "applicableConfigs" : [
      "main", "release/5.10"
    ],
    "issueUrl" : "https://github.com/apple/swift/issues/67248"
  },
  {
    "path" : "*\/ACHNBrowserUI\/ACHNBrowserUI\/ACHNBrowserUI\/views\/userLists\/UserListDetailView.swift",
    "modification" : "unmodified",
    "issueDetail" : {
      "kind" : "typeContextInfo",
      "offset" : 2922
    },
    "applicableConfigs" : [
      "main", "release/5.10"
    ],
    "issueUrl" : "https://github.com/apple/swift/issues/67248"
  },
  {
    "path" : "*\/ACHNBrowserUI\/ACHNBrowserUI\/ACHNBrowserUI\/viewModels\/ItemsViewModel.swift",
    "modification" : "insideOut-526",
    "issueDetail" : {
      "kind" : "rangeInfo",
      "length" : 16,
      "offset" : 135
    },
    "applicableConfigs" : [
      "main", "release/5.10"
    ],
    "issueUrl" : "https://github.com/apple/swift/issues/67248"
  },
  {
    "path" : "*\/ACHNBrowserUI\/ACHNBrowserUI\/ACHNBrowserUI\/views\/todayDashboard\/TodayTurnipSection.swift",
    "modification" : "insideOut-1002",
    "issueDetail" : {
      "kind" : "cursorInfo",
      "offset" : 37
    },
    "applicableConfigs" : [
      "main", "release/5.10"
    ],
    "issueUrl" : "https://github.com/apple/swift/issues/67248"
  },
  {
    "path" : "*\/ACHNBrowserUI\/ACHNBrowserUI\/ACHNBrowserUI\/views\/todayDashboard\/TodayTurnipSection.swift",
    "modification" : "insideOut-1002",
    "issueDetail" : {
      "kind" : "rangeInfo",
      "length" : 29,
      "offset" : 17
    },
    "applicableConfigs" : [
      "main", "release/5.10"
    ],
    "issueUrl" : "https://github.com/apple/swift/issues/67248"
  },
  {
    "path" : "*\/ACHNBrowserUI\/ACHNBrowserUI\/ACHNBrowserUI\/views\/todayDashboard\/TodayTurnipSection.swift",
    "modification" : "insideOut-1005",
    "issueDetail" : {
      "kind" : "cursorInfo",
      "offset" : 46
    },
    "applicableConfigs" : [
      "main", "release/5.10"
    ],
    "issueUrl" : "https://github.com/apple/swift/issues/67248"
  },
  {
    "path" : "*\/ACHNBrowserUI\/ACHNBrowserUI\/ACHNBrowserUI\/views\/todayDashboard\/TodayTurnipSection.swift",
    "modification" : "insideOut-1006",
    "issueDetail" : {
      "kind" : "rangeInfo",
      "length" : 7,
      "offset" : 946
    },
    "applicableConfigs" : [
      "main", "release/5.10"
    ],
    "issueUrl" : "https://github.com/apple/swift/issues/67248"
  },
  {
    "path" : "*\/ACHNBrowserUI\/ACHNBrowserUI\/ACHNBrowserUI\/views\/todayDashboard\/TodayTurnipSection.swift",
    "modification" : "insideOut-1018",
    "issueDetail" : {
      "kind" : "cursorInfo",
      "offset" : 1007
    },
    "applicableConfigs" : [
      "main", "release/5.10"
    ],
    "issueUrl" : "https://github.com/apple/swift/issues/67248"
  },
  {
    "path" : "*\/ACHNBrowserUI\/ACHNBrowserUI\/ACHNBrowserUI\/views\/todayDashboard\/TodayTurnipSection.swift",
    "modification" : "insideOut-1018",
    "issueDetail" : {
      "kind" : "rangeInfo",
      "length" : 42,
      "offset" : 976
    },
    "applicableConfigs" : [
      "main", "release/5.10"
    ],
    "issueUrl" : "https://github.com/apple/swift/issues/67248"
  },
  {
    "path" : "*\/ACHNBrowserUI\/ACHNBrowserUI\/ACHNBrowserUI\/views\/todayDashboard\/TodayTurnipSection.swift",
    "modification" : "insideOut-1039",
    "issueDetail" : {
      "kind" : "collectExpressionType"
    },
    "applicableConfigs" : [
      "main", "release/5.10"
    ],
    "issueUrl" : "https://github.com/apple/swift/issues/67248"
  },
  {
    "path" : "*\/ACHNBrowserUI\/ACHNBrowserUI\/ACHNBrowserUI\/views\/todayDashboard\/TodayTurnipSection.swift",
    "modification" : "insideOut-1041",
    "issueDetail" : {
      "kind" : "rangeInfo",
      "length" : 4,
      "offset" : 68
    },
    "applicableConfigs" : [
      "main", "release/5.10"
    ],
    "issueUrl" : "https://github.com/apple/swift/issues/67248"
  },
  {
    "path" : "*\/ACHNBrowserUI\/ACHNBrowserUI\/ACHNBrowserUI\/views\/todayDashboard\/TodayTurnipSection.swift",
    "modification" : "insideOut-1042",
    "issueDetail" : {
      "kind" : "rangeInfo",
      "length" : 4,
      "offset" : 69
    },
    "applicableConfigs" : [
      "main", "release/5.10"
    ],
    "issueUrl" : "https://github.com/apple/swift/issues/67248"
  },
  {
    "path" : "*\/ACHNBrowserUI\/ACHNBrowserUI\/ACHNBrowserUI\/views\/todayDashboard\/TodayTurnipSection.swift",
    "modification" : "insideOut-1059",
    "issueDetail" : {
      "kind" : "collectExpressionType"
    },
    "applicableConfigs" : [
      "main", "release/5.10"
    ],
    "issueUrl" : "https://github.com/apple/swift/issues/67248"
  },
  {
    "path" : "*\/ACHNBrowserUI\/ACHNBrowserUI\/ACHNBrowserUI\/views\/todayDashboard\/TodayTurnipSection.swift",
    "modification" : "insideOut-1064",
    "issueDetail" : {
      "kind" : "cursorInfo",
      "offset" : 90
    },
    "applicableConfigs" : [
      "main", "release/5.10"
    ],
    "issueUrl" : "https://github.com/apple/swift/issues/67248"
  },
  {
    "path" : "*\/ACHNBrowserUI\/ACHNBrowserUI\/ACHNBrowserUI\/views\/todayDashboard\/TodayTurnipSection.swift",
    "modification" : "insideOut-1084",
    "issueDetail" : {
      "kind" : "conformingMethodList",
      "offset" : 1012
    },
    "applicableConfigs" : [
      "main", "release/5.10"
    ],
    "issueUrl" : "https://github.com/apple/swift/issues/67248"
  },
  {
    "path" : "*\/ACHNBrowserUI\/ACHNBrowserUI\/ACHNBrowserUI\/views\/todayDashboard\/TodayTurnipSection.swift",
    "modification" : "insideOut-1086",
    "issueDetail" : {
      "kind" : "codeComplete",
      "offset" : 1044
    },
    "applicableConfigs" : [
      "main", "release/5.10"
    ],
    "issueUrl" : "https://github.com/apple/swift/issues/67248"
  },
  {
    "path" : "*\/ACHNBrowserUI\/ACHNBrowserUI\/ACHNBrowserUI\/views\/todayDashboard\/TodayTurnipSection.swift",
    "modification" : "insideOut-1315",
    "issueDetail" : {
      "kind" : "codeComplete",
      "offset" : 1203
    },
    "applicableConfigs" : [
      "main", "release/5.10"
    ],
    "issueUrl" : "https://github.com/apple/swift/issues/67248"
  },
  {
    "path" : "*\/ACHNBrowserUI\/ACHNBrowserUI\/ACHNBrowserUI\/views\/todayDashboard\/TodayTurnipSection.swift",
    "modification" : "insideOut-1367",
    "issueDetail" : {
      "kind" : "codeComplete",
      "offset" : 1203
    },
    "applicableConfigs" : [
      "main", "release/5.10"
    ],
    "issueUrl" : "https://github.com/apple/swift/issues/67248"
  },
  {
    "path" : "*\/ACHNBrowserUI\/ACHNBrowserUI\/ACHNBrowserUI\/views\/todayDashboard\/TodayTurnipSection.swift",
    "modification" : "insideOut-836",
    "issueDetail" : {
      "kind" : "codeComplete",
      "offset" : 836
    },
    "applicableConfigs" : [
      "main", "release/5.10"
    ],
    "issueUrl" : "https://github.com/apple/swift/issues/67248"
  },
  {
    "path" : "*\/ACHNBrowserUI\/ACHNBrowserUI\/ACHNBrowserUI\/views\/todayDashboard\/TodayTurnipSection.swift",
    "modification" : "insideOut-1084",
    "issueDetail" : {
      "kind" : "codeComplete",
      "offset" : 1012
    },
    "applicableConfigs" : [
      "main", "release/5.10"
    ],
    "issueUrl" : "https://github.com/apple/swift/issues/67248"
  },
  {
    "path" : "*\/ACHNBrowserUI\/ACHNBrowserUI\/ACHNBrowserUI\/views\/todayDashboard\/TodayTurnipSection.swift",
    "modification" : "insideOut-1443",
    "issueDetail" : {
      "kind" : "codeComplete",
      "offset" : 1255
    },
    "applicableConfigs" : [
      "main", "release/5.10"
    ],
    "issueUrl" : "https://github.com/apple/swift/issues/67248"
  },
  {
    "path" : "*\/ACHNBrowserUI\/ACHNBrowserUI\/ACHNBrowserUI\/views\/todayDashboard\/TodayTurnipSection.swift",
    "modification" : "insideOut-1460",
    "issueDetail" : {
      "kind" : "codeComplete",
      "offset" : 1255
    },
    "applicableConfigs" : [
      "main", "release/5.10"
    ],
    "issueUrl" : "https://github.com/apple/swift/issues/67248"
  },
  {
    "path" : "*\/ACHNBrowserUI\/ACHNBrowserUI\/ACHNBrowserUI\/views\/turnips\/charts\/TurnipsChart.swift",
    "modification" : "insideOut-166",
    "issueDetail" : {
      "kind" : "conformingMethodList",
      "offset" : 89
    },
    "applicableConfigs" : [
      "main", "release/5.10"
    ],
    "issueUrl" : "https://github.com/apple/swift/issues/67248"
  },
  {
    "path" : "*\/ACHNBrowserUI\/ACHNBrowserUI\/ACHNBrowserUI\/views\/turnips\/charts\/TurnipsChart.swift",
    "modification" : "insideOut-168",
    "issueDetail" : {
      "kind" : "codeComplete",
      "offset" : 122
    },
    "applicableConfigs" : [
      "main", "release/5.10"
    ],
    "issueUrl" : "https://github.com/apple/swift/issues/67248"
  },
  {
    "path" : "*\/MovieSwift\/MovieSwift\/MovieSwift\/views\/components\/discover\/DraggableCover.swift",
    "modification" : "insideOut-226",
    "issueDetail" : {
      "kind" : "codeComplete",
      "offset" : 72
    },
    "applicableConfigs" : [
      "release\/5.9"
    ],
    "issueUrl" : "https://github.com/apple/swift/issues/67248"
  },
  {
    "path" : "*\/MovieSwift\/MovieSwift\/MovieSwift\/views\/components\/discover\/DraggableCover.swift",
    "modification" : "insideOut-226",
    "issueDetail" : {
      "kind" : "typeContextInfo",
      "offset" : 72
    },
    "applicableConfigs" : [
      "release\/5.9"
    ],
    "issueUrl" : "https://github.com/apple/swift/issues/67248"
  },
  {
    "path" : "*\/MovieSwift\/MovieSwift\/MovieSwift\/views\/components\/discover\/DraggableCover.swift",
    "modification" : "insideOut-227",
    "issueDetail" : {
      "kind" : "codeComplete",
      "offset" : 73
    },
    "applicableConfigs" : [
      "release\/5.9"
    ],
    "issueUrl" : "https://github.com/apple/swift/issues/67248"
  },
  {
    "path" : "*\/MovieSwift\/MovieSwift\/MovieSwift\/views\/components\/discover\/DraggableCover.swift",
    "modification" : "insideOut-227",
    "issueDetail" : {
      "kind" : "typeContextInfo",
      "offset" : 73
    },
    "applicableConfigs" : [
      "release\/5.9"
    ],
    "issueUrl" : "https://github.com/apple/swift/issues/67248"
  },
  {
    "path" : "*\/ACHNBrowserUI\/ACHNBrowserUI\/ACHNBrowserUI\/views\/turnips\/charts\/TurnipsChart.swift",
    "modification" : "insideOut-166",
    "issueDetail" : {
      "kind" : "codeComplete",
      "offset" : 89
    },
    "applicableConfigs" : [
      "main"
    ],
    "issueUrl" : "https://github.com/apple/swift/issues/67248"
  },
  {
    "path" : "*\/ACHNBrowserUI\/ACHNBrowserUI\/ACHNBrowserUI\/views\/turnips\/charts\/TurnipsChart.swift",
    "modification" : "insideOut-166",
    "issueDetail" : {
      "kind" : "codeComplete",
      "offset" : 89
    },
    "applicableConfigs" : [
      "main"
    ],
    "issueUrl" : "https://github.com/apple/swift/issues/67248"
  },
  {
    "path" : "*\/ACHNBrowserUI\/ACHNBrowserUI\/ACHNBrowserUI\/views\/turnips\/TurnipsView.swift",
    "modification" : "unmodified",
    "issueDetail" : {
      "kind" : "codeComplete",
      "offset" : 6622
    },
    "applicableConfigs" : [
      "main"
    ],
    "issueUrl" : "https://github.com/apple/swift/issues/67248"
  },
  {
    "path" : "*\/ACHNBrowserUI\/ACHNBrowserUI\/ACHNBrowserUI\/views\/turnips\/charts\/TurnipsChart.swift",
    "modification" : "insideOut-168",
    "issueDetail" : {
      "kind" : "conformingMethodList",
      "offset" : 122
    },
    "applicableConfigs" : [
      "main"
    ],
    "issueUrl" : "https://github.com/apple/swift/issues/67248"
  },
  {
    "path" : "*\/ACHNBrowserUI\/ACHNBrowserUI\/ACHNBrowserUI\/views\/listing\/ListingRow.swift",
    "modification" : "unmodified",
    "issueDetail" : {
      "kind" : "codeComplete",
      "offset" : 237
    },
    "applicableConfigs" : [
      "main"
    ],
    "issueUrl" : "https://github.com/apple/swift/issues/67248"
  },
  {
    "path" : "*\/ACHNBrowserUI\/ACHNBrowserUI\/ACHNBrowserUI\/viewModifiers\/AdaptsToSoftwareKeyboard.swift",
    "modification" : "unmodified",
    "issueDetail" : {
      "kind" : "codeComplete",
      "offset" : 962
    },
    "applicableConfigs" : [
      "main"
    ],
    "issueUrl" : "https://github.com/apple/swift/issues/69936"
  },
  {
    "path" : "*\/ACHNBrowserUI\/ACHNBrowserUI\/ACHNBrowserUI\/viewModifiers\/AdaptsToSoftwareKeyboard.swift",
    "modification" : "unmodified",
    "issueDetail" : {
      "kind" : "codeComplete",
      "offset" : 1247
    },
    "applicableConfigs" : [
      "main"
    ],
    "issueUrl" : "https://github.com/apple/swift/issues/69936"
  }
]
